{
  "resourceType": "Practitioner",
  "id": "InstanceOfPractitionerCarstenSchmidt",
  "meta": {
    "profile": [
      "https://www.nfdi4health.de/fhir/metadataschema/StructureDefinition/nfdi4health-pr-mds-practitioner"
    ]
  },
  "name": [
    {
      "family": "Schmidt",
      "given": [
        "Carsten Oliver"
      ],
      "prefix": [
        "C69170"
      ]
    }
  ],
  "identifier": [
    {
      "value": "0000-0001-5266-9396",
      "type": {
        "coding": [
          {
            "code": "080",
            "system": "https://www.nfdi4health.de/fhir/metadataschema/CodeSystem/nfdi4health-cs-remaining-concepts",
            "display": "ORCID"
          }
        ]
      }
    }
  ]
}
